<?xml version="1.0" encoding="utf-8" ?>
<c2layout>
    <name>M7_HeatLock</name>
    <sid>951837943827219</sid>
    <event-sheet>M7_HeatLock</event-sheet>
    <size>
        <width>1920</width>
        <height>1200</height>
    </size>
    <margins>
        <horizontal>500</horizontal>
        <vertical>500</vertical>
    </margins>
    <unbounded-scrolling>0</unbounded-scrolling>
    <layers>
        <layer name="Weather" sid="299684255942133">
            <initially-visible>1</initially-visible>
            <background-color>255,255,255</background-color>
            <transparent>1</transparent>
            <parallax>
                <x>1</x>
                <y>1</y>
            </parallax>
            <zoom-rate>1</zoom-rate>
            <opacity>1</opacity>
            <force-own-texture>0</force-own-texture>
            <global>0</global>
            <use-render-cells>0</use-render-cells>
            <blend-mode>0</blend-mode>
            <effect-fallback>0</effect-fallback>
            <instances>
                <instance type="M7_Weather" uid="1158">
                    <properties>
                        <initial-visibility>Visible</initial-visibility>
                        <initial-animation>Default</initial-animation>
                        <initial-frame>0</initial-frame>
                        <collisions>Enabled</collisions>
                    </properties>
                    <instance-variables>
                        <HasSun>0</HasSun>
                    </instance-variables>
                    <blend-mode>0</blend-mode>
                    <effect-fallback>0</effect-fallback>
                    <world>
                        <x>960</x>
                        <y>600</y>
                        <z>0</z>
                        <width>1920</width>
                        <height>1200</height>
                        <depth>0</depth>
                        <hotspotX>0.5</hotspotX>
                        <hotspotY>0.5</hotspotY>
                        <angle>0</angle>
                        <opacity>1</opacity>
                    </world>
                </instance>
            </instances>
            <effects />
        </layer>
        <layer name="Background" sid="506778839284076">
            <initially-visible>1</initially-visible>
            <background-color>255,255,255</background-color>
            <transparent>1</transparent>
            <parallax>
                <x>1</x>
                <y>1</y>
            </parallax>
            <zoom-rate>1</zoom-rate>
            <opacity>1</opacity>
            <force-own-texture>0</force-own-texture>
            <global>0</global>
            <use-render-cells>0</use-render-cells>
            <blend-mode>0</blend-mode>
            <effect-fallback>0</effect-fallback>
            <instances>
                <instance type="M7_Background" uid="1159">
                    <properties>
                        <initial-visibility>Visible</initial-visibility>
                        <initial-animation>Default</initial-animation>
                        <initial-frame>0</initial-frame>
                        <collisions>Enabled</collisions>
                    </properties>
                    <blend-mode>0</blend-mode>
                    <effect-fallback>0</effect-fallback>
                    <world>
                        <x>1061</x>
                        <y>643</y>
                        <z>0</z>
                        <width>1920</width>
                        <height>1200</height>
                        <depth>0</depth>
                        <hotspotX>0.5</hotspotX>
                        <hotspotY>0.5</hotspotY>
                        <angle>0</angle>
                        <opacity>1</opacity>
                    </world>
                </instance>
                <instance type="M7_Door5" uid="1160">
                    <properties>
                        <initial-visibility>Visible</initial-visibility>
                        <initial-animation>Default</initial-animation>
                        <initial-frame>0</initial-frame>
                        <collisions>Enabled</collisions>
                    </properties>
                    <instance-variables>
                        <Open>1</Open>
                        <Rooms></Rooms>
                        <Occupied>0</Occupied>
                    </instance-variables>
                    <blend-mode>0</blend-mode>
                    <effect-fallback>0</effect-fallback>
                    <world>
                        <x>2221</x>
                        <y>710</y>
                        <z>0</z>
                        <width>50</width>
                        <height>42</height>
                        <depth>0</depth>
                        <hotspotX>0.5</hotspotX>
                        <hotspotY>0.5</hotspotY>
                        <angle>0</angle>
                        <opacity>1</opacity>
                    </world>
                </instance>
                <instance type="M7_Vent" uid="1161">
                    <properties>
                        <initial-visibility>Visible</initial-visibility>
                        <initial-animation>0C</initial-animation>
                        <initial-frame>0</initial-frame>
                        <collisions>Enabled</collisions>
                    </properties>
                    <blend-mode>0</blend-mode>
                    <effect-fallback>0</effect-fallback>
                    <world>
                        <x>769</x>
                        <y>388</y>
                        <z>0</z>
                        <width>170</width>
                        <height>77</height>
                        <depth>0</depth>
                        <hotspotX>0.494117647</hotspotX>
                        <hotspotY>0.532467544</hotspotY>
                        <angle>0</angle>
                        <opacity>1</opacity>
                    </world>
                </instance>
                <instance type="M7_Vent" uid="1162">
                    <properties>
                        <initial-visibility>Visible</initial-visibility>
                        <initial-animation>0C</initial-animation>
                        <initial-frame>0</initial-frame>
                        <collisions>Enabled</collisions>
                    </properties>
                    <blend-mode>0</blend-mode>
                    <effect-fallback>0</effect-fallback>
                    <world>
                        <x>946</x>
                        <y>814</y>
                        <z>0</z>
                        <width>170</width>
                        <height>77</height>
                        <depth>0</depth>
                        <hotspotX>0.494117647</hotspotX>
                        <hotspotY>0.532467544</hotspotY>
                        <angle>0</angle>
                        <opacity>1</opacity>
                    </world>
                </instance>
                <instance type="M7_Vent" uid="1163">
                    <properties>
                        <initial-visibility>Visible</initial-visibility>
                        <initial-animation>0C</initial-animation>
                        <initial-frame>0</initial-frame>
                        <collisions>Enabled</collisions>
                    </properties>
                    <blend-mode>0</blend-mode>
                    <effect-fallback>0</effect-fallback>
                    <world>
                        <x>1669</x>
                        <y>773</y>
                        <z>0</z>
                        <width>170</width>
                        <height>77</height>
                        <depth>0</depth>
                        <hotspotX>0.494117647</hotspotX>
                        <hotspotY>0.532467544</hotspotY>
                        <angle>0</angle>
                        <opacity>1</opacity>
                    </world>
                </instance>
                <instance type="M7_Thermostat" uid="1183">
                    <properties>
                        <initial-visibility>Visible</initial-visibility>
                        <initial-animation>Default</initial-animation>
                        <initial-frame>0</initial-frame>
                        <collisions>Enabled</collisions>
                    </properties>
                    <blend-mode>0</blend-mode>
                    <effect-fallback>0</effect-fallback>
                    <world>
                        <x>274</x>
                        <y>176</y>
                        <z>0</z>
                        <width>485</width>
                        <height>275</height>
                        <depth>0</depth>
                        <hotspotX>0.5</hotspotX>
                        <hotspotY>0.5</hotspotY>
                        <angle>0</angle>
                        <opacity>1</opacity>
                    </world>
                </instance>
                <instance type="M7_ThermostatSignal" uid="931">
                    <properties>
                        <initial-visibility>Visible</initial-visibility>
                        <initial-animation>Default</initial-animation>
                        <initial-frame>0</initial-frame>
                        <collisions>Enabled</collisions>
                    </properties>
                    <instance-variables>
                        <totalSteps>0</totalSteps>
                        <timer>0</timer>
                        <distance>0</distance>
                        <flag>0</flag>
                    </instance-variables>
                    <effect-instances>
                        <effect-instance type="ScanLines">
                            <parameters>
                                <line-height>2</line-height>
                            </parameters>
                        </effect-instance>
                        <effect-instance type="WarpRipple">
                            <parameters>
                                <amplitude>0.02</amplitude>
                                <frequency>3</frequency>
                                <speed>-2</speed>
                            </parameters>
                        </effect-instance>
                    </effect-instances>
                    <blend-mode>0</blend-mode>
                    <effect-fallback>0</effect-fallback>
                    <world>
                        <x>-220</x>
                        <y>534</y>
                        <z>0</z>
                        <width>150</width>
                        <height>240</height>
                        <depth>0</depth>
                        <hotspotX>0.479999989</hotspotX>
                        <hotspotY>0.512499988</hotspotY>
                        <angle>0</angle>
                        <opacity>0.600000024</opacity>
                    </world>
                </instance>
            </instances>
            <effects />
        </layer>
        <layer name="People" sid="892023054001207">
            <initially-visible>1</initially-visible>
            <background-color>255,255,255</background-color>
            <transparent>1</transparent>
            <parallax>
                <x>1</x>
                <y>1</y>
            </parallax>
            <zoom-rate>1</zoom-rate>
            <opacity>1</opacity>
            <force-own-texture>0</force-own-texture>
            <global>0</global>
            <use-render-cells>0</use-render-cells>
            <blend-mode>0</blend-mode>
            <effect-fallback>0</effect-fallback>
            <instances>
                <instance type="M7_Person1" uid="1164">
                    <properties>
                        <initial-visibility>Visible</initial-visibility>
                        <initial-animation>Default</initial-animation>
                        <initial-frame>0</initial-frame>
                        <collisions>Enabled</collisions>
                    </properties>
                    <instance-variables>
                        <State>waiting</State>
                        <WaitingTimer>0</WaitingTimer>
                        <Speed>200</Speed>
                        <MovementAngle>0</MovementAngle>
                        <ChosenRoom>0</ChosenRoom>
                        <PreviousRoom>0</PreviousRoom>
                    </instance-variables>
                    <behavior-instances>
                        <behavior-instance type="CustomMovement">
                            <properties>
                                <stepping-mode>None</stepping-mode>
                                <pixels-per-step>5</pixels-per-step>
                                <initial-state>Enabled</initial-state>
                            </properties>
                        </behavior-instance>
                    </behavior-instances>
                    <blend-mode>0</blend-mode>
                    <effect-fallback>0</effect-fallback>
                    <world>
                        <x>2351</x>
                        <y>435</y>
                        <z>0</z>
                        <width>126.306816101</width>
                        <height>236.363632202</height>
                        <depth>0</depth>
                        <hotspotX>0.491228074</hotspotX>
                        <hotspotY>1.006451607</hotspotY>
                        <angle>0</angle>
                        <opacity>1</opacity>
                    </world>
                </instance>
                <instance type="M7_Person2" uid="1165">
                    <properties>
                        <initial-visibility>Visible</initial-visibility>
                        <initial-animation>Default</initial-animation>
                        <initial-frame>0</initial-frame>
                        <collisions>Enabled</collisions>
                    </properties>
                    <instance-variables>
                        <State>waiting</State>
                        <WaitingTimer>0</WaitingTimer>
                        <Speed>200</Speed>
                        <MovementAngle>0</MovementAngle>
                        <ChosenRoom>0</ChosenRoom>
                        <PreviousRoom>0</PreviousRoom>
                    </instance-variables>
                    <behavior-instances>
                        <behavior-instance type="CustomMovement">
                            <properties>
                                <stepping-mode>None</stepping-mode>
                                <pixels-per-step>5</pixels-per-step>
                                <initial-state>Enabled</initial-state>
                            </properties>
                        </behavior-instance>
                    </behavior-instances>
                    <blend-mode>0</blend-mode>
                    <effect-fallback>0</effect-fallback>
                    <world>
                        <x>2219</x>
                        <y>390</y>
                        <z>0</z>
                        <width>121.558441162</width>
                        <height>234.8387146</height>
                        <depth>0</depth>
                        <hotspotX>0.513888896</hotspotX>
                        <hotspotY>0.993506491</hotspotY>
                        <angle>0</angle>
                        <opacity>1</opacity>
                    </world>
                </instance>
                <instance type="M7_Person3" uid="1166">
                    <properties>
                        <initial-visibility>Visible</initial-visibility>
                        <initial-animation>Default</initial-animation>
                        <initial-frame>0</initial-frame>
                        <collisions>Enabled</collisions>
                    </properties>
                    <instance-variables>
                        <State>waiting</State>
                        <WaitingTimer>0</WaitingTimer>
                        <Speed>200</Speed>
                        <MovementAngle>0</MovementAngle>
                        <ChosenRoom>0</ChosenRoom>
                        <PreviousRoom>0</PreviousRoom>
                    </instance-variables>
                    <behavior-instances>
                        <behavior-instance type="CustomMovement">
                            <properties>
                                <stepping-mode>None</stepping-mode>
                                <pixels-per-step>5</pixels-per-step>
                                <initial-state>Enabled</initial-state>
                            </properties>
                        </behavior-instance>
                    </behavior-instances>
                    <blend-mode>0</blend-mode>
                    <effect-fallback>0</effect-fallback>
                    <world>
                        <x>2422</x>
                        <y>689</y>
                        <z>0</z>
                        <width>126</width>
                        <height>236</height>
                        <depth>0</depth>
                        <hotspotX>0.491228074</hotspotX>
                        <hotspotY>1.006451607</hotspotY>
                        <angle>0</angle>
                        <opacity>1</opacity>
                    </world>
                </instance>
            </instances>
            <effects />
        </layer>
        <layer name="Rooms" sid="817633482906646">
            <initially-visible>1</initially-visible>
            <background-color>255,255,255</background-color>
            <transparent>1</transparent>
            <parallax>
                <x>1</x>
                <y>1</y>
            </parallax>
            <zoom-rate>1</zoom-rate>
            <opacity>1</opacity>
            <force-own-texture>0</force-own-texture>
            <global>0</global>
            <use-render-cells>0</use-render-cells>
            <blend-mode>0</blend-mode>
            <effect-fallback>0</effect-fallback>
            <instances>
                <instance type="M7_stairs_hack" uid="1167">
                    <properties>
                        <initial-visibility>Visible</initial-visibility>
                        <initial-animation>Default</initial-animation>
                        <initial-frame>0</initial-frame>
                        <collisions>Enabled</collisions>
                    </properties>
                    <blend-mode>0</blend-mode>
                    <effect-fallback>0</effect-fallback>
                    <world>
                        <x>1430</x>
                        <y>697</y>
                        <z>0</z>
                        <width>210</width>
                        <height>41</height>
                        <depth>0</depth>
                        <hotspotX>0.504761934</hotspotX>
                        <hotspotY>0.439024389</hotspotY>
                        <angle>0</angle>
                        <opacity>1</opacity>
                    </world>
                </instance>
                <instance type="M7_Room0" uid="1168">
                    <properties>
                        <initial-visibility>Visible</initial-visibility>
                        <initial-animation>Default</initial-animation>
                        <initial-frame>0</initial-frame>
                        <collisions>Enabled</collisions>
                    </properties>
                    <instance-variables>
                        <Temperature>1</Temperature>
                        <OldTemperature>1</OldTemperature>
                        <VentCount>0</VentCount>
                        <Neighbours></Neighbours>
                        <Windows></Windows>
                        <Doors></Doors>
                        <StoveCount>0</StoveCount>
                        <ExtraHeatPerSecond>0</ExtraHeatPerSecond>
                        <Maxheight>0</Maxheight>
                    </instance-variables>
                    <blend-mode>0</blend-mode>
                    <effect-fallback>0</effect-fallback>
                    <world>
                        <x>448</x>
                        <y>712</y>
                        <z>0</z>
                        <width>321.303527832</width>
                        <height>400.906188965</height>
                        <depth>0</depth>
                        <hotspotX>0.5</hotspotX>
                        <hotspotY>1</hotspotY>
                        <angle>0</angle>
                        <opacity>1</opacity>
                    </world>
                </instance>
                <instance type="M7_Room1" uid="1169">
                    <properties>
                        <initial-visibility>Visible</initial-visibility>
                        <initial-animation>Default</initial-animation>
                        <initial-frame>0</initial-frame>
                        <collisions>Enabled</collisions>
                    </properties>
                    <instance-variables>
                        <Temperature>1</Temperature>
                        <OldTemperature>1</OldTemperature>
                        <VentCount>1</VentCount>
                        <Neighbours></Neighbours>
                        <Windows></Windows>
                        <Doors></Doors>
                        <StoveCount>0</StoveCount>
                        <ExtraHeatPerSecond>0.2</ExtraHeatPerSecond>
                        <Maxheight>0</Maxheight>
                    </instance-variables>
                    <blend-mode>0</blend-mode>
                    <effect-fallback>0</effect-fallback>
                    <world>
                        <x>910</x>
                        <y>711</y>
                        <z>0</z>
                        <width>577.487731934</width>
                        <height>399.062316895</height>
                        <depth>0</depth>
                        <hotspotX>0.5</hotspotX>
                        <hotspotY>1</hotspotY>
                        <angle>0</angle>
                        <opacity>1</opacity>
                    </world>
                </instance>
                <instance type="M7_Room2" uid="1170">
                    <properties>
                        <initial-visibility>Visible</initial-visibility>
                        <initial-animation>Default</initial-animation>
                        <initial-frame>0</initial-frame>
                        <collisions>Enabled</collisions>
                    </properties>
                    <instance-variables>
                        <Temperature>1</Temperature>
                        <OldTemperature>1</OldTemperature>
                        <VentCount>0</VentCount>
                        <Neighbours></Neighbours>
                        <Windows></Windows>
                        <Doors></Doors>
                        <StoveCount>0</StoveCount>
                        <ExtraHeatPerSecond>0</ExtraHeatPerSecond>
                        <Maxheight>0</Maxheight>
                    </instance-variables>
                    <blend-mode>0</blend-mode>
                    <effect-fallback>0</effect-fallback>
                    <world>
                        <x>1433</x>
                        <y>681</y>
                        <z>0</z>
                        <width>567</width>
                        <height>398</height>
                        <depth>0</depth>
                        <hotspotX>0.388007045</hotspotX>
                        <hotspotY>0.927135706</hotspotY>
                        <angle>0</angle>
                        <opacity>1</opacity>
                    </world>
                </instance>
                <instance type="M7_Room3" uid="1171">
                    <properties>
                        <initial-visibility>Visible</initial-visibility>
                        <initial-animation>Default</initial-animation>
                        <initial-frame>0</initial-frame>
                        <collisions>Enabled</collisions>
                    </properties>
                    <instance-variables>
                        <Temperature>1</Temperature>
                        <OldTemperature>1</OldTemperature>
                        <VentCount>0</VentCount>
                        <Neighbours></Neighbours>
                        <Windows></Windows>
                        <Doors></Doors>
                        <StoveCount>0</StoveCount>
                        <ExtraHeatPerSecond>0</ExtraHeatPerSecond>
                        <Maxheight>0</Maxheight>
                    </instance-variables>
                    <blend-mode>0</blend-mode>
                    <effect-fallback>0</effect-fallback>
                    <world>
                        <x>537</x>
                        <y>1123</y>
                        <z>0</z>
                        <width>496.614105225</width>
                        <height>399.656921387</height>
                        <depth>0</depth>
                        <hotspotX>0.5</hotspotX>
                        <hotspotY>1</hotspotY>
                        <angle>0</angle>
                        <opacity>1</opacity>
                    </world>
                </instance>
                <instance type="M7_Room4" uid="1172">
                    <properties>
                        <initial-visibility>Visible</initial-visibility>
                        <initial-animation>Default</initial-animation>
                        <initial-frame>0</initial-frame>
                        <collisions>Enabled</collisions>
                    </properties>
                    <instance-variables>
                        <Temperature>1</Temperature>
                        <OldTemperature>1</OldTemperature>
                        <VentCount>1</VentCount>
                        <Neighbours></Neighbours>
                        <Windows></Windows>
                        <Doors></Doors>
                        <StoveCount>1</StoveCount>
                        <ExtraHeatPerSecond>0.3</ExtraHeatPerSecond>
                        <Maxheight>0</Maxheight>
                    </instance-variables>
                    <blend-mode>0</blend-mode>
                    <effect-fallback>0</effect-fallback>
                    <world>
                        <x>1047</x>
                        <y>1122</y>
                        <z>0</z>
                        <width>496.978881836</width>
                        <height>398.000488281</height>
                        <depth>0</depth>
                        <hotspotX>0.5</hotspotX>
                        <hotspotY>1</hotspotY>
                        <angle>0</angle>
                        <opacity>1</opacity>
                    </world>
                </instance>
                <instance type="M7_Room5" uid="1173">
                    <properties>
                        <initial-visibility>Visible</initial-visibility>
                        <initial-animation>Default</initial-animation>
                        <initial-frame>0</initial-frame>
                        <collisions>Enabled</collisions>
                    </properties>
                    <instance-variables>
                        <Temperature>1</Temperature>
                        <OldTemperature>1</OldTemperature>
                        <VentCount>0</VentCount>
                        <Neighbours></Neighbours>
                        <Windows></Windows>
                        <Doors></Doors>
                        <StoveCount>0</StoveCount>
                        <ExtraHeatPerSecond>0</ExtraHeatPerSecond>
                        <Maxheight>0</Maxheight>
                    </instance-variables>
                    <blend-mode>0</blend-mode>
                    <effect-fallback>0</effect-fallback>
                    <world>
                        <x>1428</x>
                        <y>1121</y>
                        <z>0</z>
                        <width>239.290283203</width>
                        <height>397.584899902</height>
                        <depth>0</depth>
                        <hotspotX>0.5</hotspotX>
                        <hotspotY>1</hotspotY>
                        <angle>0</angle>
                        <opacity>1</opacity>
                    </world>
                </instance>
                <instance type="M7_Room6" uid="1174">
                    <properties>
                        <initial-visibility>Visible</initial-visibility>
                        <initial-animation>Default</initial-animation>
                        <initial-frame>0</initial-frame>
                        <collisions>Enabled</collisions>
                    </properties>
                    <instance-variables>
                        <Temperature>1</Temperature>
                        <OldTemperature>1</OldTemperature>
                        <VentCount>1</VentCount>
                        <Neighbours></Neighbours>
                        <Windows></Windows>
                        <Doors></Doors>
                        <StoveCount>0</StoveCount>
                        <ExtraHeatPerSecond>0.2</ExtraHeatPerSecond>
                        <Maxheight>0</Maxheight>
                    </instance-variables>
                    <blend-mode>0</blend-mode>
                    <effect-fallback>0</effect-fallback>
                    <world>
                        <x>1720</x>
                        <y>1121</y>
                        <z>0</z>
                        <width>219.815551758</width>
                        <height>398.682128906</height>
                        <depth>0</depth>
                        <hotspotX>0.716000021</hotspotX>
                        <hotspotY>0.995999992</hotspotY>
                        <angle>0</angle>
                        <opacity>1</opacity>
                    </world>
                </instance>
            </instances>
            <effects />
        </layer>
        <layer name="Objects" sid="578079967503517">
            <initially-visible>1</initially-visible>
            <background-color>255,255,255</background-color>
            <transparent>1</transparent>
            <parallax>
                <x>1</x>
                <y>1</y>
            </parallax>
            <zoom-rate>1</zoom-rate>
            <opacity>1</opacity>
            <force-own-texture>0</force-own-texture>
            <global>0</global>
            <use-render-cells>0</use-render-cells>
            <blend-mode>0</blend-mode>
            <effect-fallback>0</effect-fallback>
            <instances>
                <instance type="M7_Door0" uid="1175">
                    <properties>
                        <initial-visibility>Visible</initial-visibility>
                        <initial-animation>Default</initial-animation>
                        <initial-frame>0</initial-frame>
                        <collisions>Enabled</collisions>
                    </properties>
                    <instance-variables>
                        <Open>0</Open>
                        <Rooms></Rooms>
                        <Occupied>0</Occupied>
                    </instance-variables>
                    <blend-mode>0</blend-mode>
                    <effect-fallback>0</effect-fallback>
                    <world>
                        <x>616</x>
                        <y>589</y>
                        <z>0</z>
                        <width>200</width>
                        <height>300</height>
                        <depth>0</depth>
                        <hotspotX>0.460000008</hotspotX>
                        <hotspotY>0.5</hotspotY>
                        <angle>0</angle>
                        <opacity>1</opacity>
                    </world>
                </instance>
                <instance type="M7_Window0" uid="1176">
                    <properties>
                        <initial-visibility>Visible</initial-visibility>
                        <initial-animation>Default</initial-animation>
                        <initial-frame>0</initial-frame>
                        <collisions>Enabled</collisions>
                    </properties>
                    <instance-variables>
                        <Open>0</Open>
                        <HasSun>0</HasSun>
                        <WeatherInfluence>1</WeatherInfluence>
                    </instance-variables>
                    <blend-mode>0</blend-mode>
                    <effect-fallback>0</effect-fallback>
                    <world>
                        <x>282</x>
                        <y>479</y>
                        <z>0</z>
                        <width>202.105255127</width>
                        <height>250</height>
                        <depth>0</depth>
                        <hotspotX>0.487500012</hotspotX>
                        <hotspotY>0.5</hotspotY>
                        <angle>0</angle>
                        <opacity>1</opacity>
                    </world>
                </instance>
                <instance type="M7_Window1" uid="1177">
                    <properties>
                        <initial-visibility>Visible</initial-visibility>
                        <initial-animation>Default</initial-animation>
                        <initial-frame>0</initial-frame>
                        <collisions>Enabled</collisions>
                    </properties>
                    <instance-variables>
                        <Open>0</Open>
                        <HasSun>0</HasSun>
                        <WeatherInfluence>1</WeatherInfluence>
                    </instance-variables>
                    <blend-mode>0</blend-mode>
                    <effect-fallback>0</effect-fallback>
                    <world>
                        <x>282</x>
                        <y>896</y>
                        <z>0</z>
                        <width>192</width>
                        <height>240.437164307</height>
                        <depth>0</depth>
                        <hotspotX>0.456250012</hotspotX>
                        <hotspotY>0.5</hotspotY>
                        <angle>0</angle>
                        <opacity>1</opacity>
                    </world>
                </instance>
                <instance type="M7_Window2" uid="1178">
                    <properties>
                        <initial-visibility>Visible</initial-visibility>
                        <initial-animation>Default</initial-animation>
                        <initial-frame>0</initial-frame>
                        <collisions>Enabled</collisions>
                    </properties>
                    <instance-variables>
                        <Open>0</Open>
                        <HasSun>0</HasSun>
                        <WeatherInfluence>0</WeatherInfluence>
                    </instance-variables>
                    <blend-mode>0</blend-mode>
                    <effect-fallback>0</effect-fallback>
                    <world>
                        <x>1788</x>
                        <y>895</y>
                        <z>0</z>
                        <width>192</width>
                        <height>240.437164307</height>
                        <depth>0</depth>
                        <hotspotX>0.543749988</hotspotX>
                        <hotspotY>0.5</hotspotY>
                        <angle>0</angle>
                        <opacity>1</opacity>
                    </world>
                </instance>
                <instance type="M7_Door1" uid="1179">
                    <properties>
                        <initial-visibility>Visible</initial-visibility>
                        <initial-animation>Default</initial-animation>
                        <initial-frame>0</initial-frame>
                        <collisions>Enabled</collisions>
                    </properties>
                    <instance-variables>
                        <Open>0</Open>
                        <Rooms></Rooms>
                        <Occupied>0</Occupied>
                    </instance-variables>
                    <blend-mode>0</blend-mode>
                    <effect-fallback>0</effect-fallback>
                    <world>
                        <x>1203</x>
                        <y>588</y>
                        <z>0</z>
                        <width>200</width>
                        <height>300</height>
                        <depth>0</depth>
                        <hotspotX>0.545000017</hotspotX>
                        <hotspotY>0.50666666</hotspotY>
                        <angle>0</angle>
                        <opacity>1</opacity>
                    </world>
                </instance>
                <instance type="M7_Door2" uid="1180">
                    <properties>
                        <initial-visibility>Visible</initial-visibility>
                        <initial-animation>Default</initial-animation>
                        <initial-frame>0</initial-frame>
                        <collisions>Enabled</collisions>
                    </properties>
                    <instance-variables>
                        <Open>0</Open>
                        <Rooms></Rooms>
                        <Occupied>0</Occupied>
                    </instance-variables>
                    <blend-mode>0</blend-mode>
                    <effect-fallback>0</effect-fallback>
                    <world>
                        <x>793</x>
                        <y>1000</y>
                        <z>0</z>
                        <width>200</width>
                        <height>300</height>
                        <depth>0</depth>
                        <hotspotX>0.460000008</hotspotX>
                        <hotspotY>0.50666666</hotspotY>
                        <angle>0</angle>
                        <opacity>1</opacity>
                    </world>
                </instance>
                <instance type="M7_Door3" uid="1181">
                    <properties>
                        <initial-visibility>Visible</initial-visibility>
                        <initial-animation>Default</initial-animation>
                        <initial-frame>0</initial-frame>
                        <collisions>Enabled</collisions>
                    </properties>
                    <instance-variables>
                        <Open>0</Open>
                        <Rooms></Rooms>
                        <Occupied>0</Occupied>
                    </instance-variables>
                    <blend-mode>0</blend-mode>
                    <effect-fallback>0</effect-fallback>
                    <world>
                        <x>1302</x>
                        <y>998</y>
                        <z>0</z>
                        <width>200</width>
                        <height>300</height>
                        <depth>0</depth>
                        <hotspotX>0.460000008</hotspotX>
                        <hotspotY>0.5</hotspotY>
                        <angle>0</angle>
                        <opacity>1</opacity>
                    </world>
                </instance>
                <instance type="M7_Door4" uid="1182">
                    <properties>
                        <initial-visibility>Visible</initial-visibility>
                        <initial-animation>Default</initial-animation>
                        <initial-frame>0</initial-frame>
                        <collisions>Enabled</collisions>
                    </properties>
                    <instance-variables>
                        <Open>0</Open>
                        <Rooms></Rooms>
                        <Occupied>0</Occupied>
                    </instance-variables>
                    <blend-mode>0</blend-mode>
                    <effect-fallback>0</effect-fallback>
                    <world>
                        <x>1556</x>
                        <y>1000</y>
                        <z>0</z>
                        <width>200</width>
                        <height>300</height>
                        <depth>0</depth>
                        <hotspotX>0.460000008</hotspotX>
                        <hotspotY>0.50666666</hotspotY>
                        <angle>0</angle>
                        <opacity>1</opacity>
                    </world>
                </instance>
            </instances>
            <effects />
        </layer>
        <layer name="EndGame" sid="387417919388143">
            <initially-visible>1</initially-visible>
            <background-color>255,255,255</background-color>
            <transparent>1</transparent>
            <parallax>
                <x>1</x>
                <y>1</y>
            </parallax>
            <zoom-rate>1</zoom-rate>
            <opacity>1</opacity>
            <force-own-texture>0</force-own-texture>
            <global>0</global>
            <use-render-cells>0</use-render-cells>
            <blend-mode>0</blend-mode>
            <effect-fallback>0</effect-fallback>
            <instances>
                <instance type="M7_End_Dim" uid="1187">
                    <properties>
                        <initial-visibility>Visible</initial-visibility>
                        <initial-animation>Default</initial-animation>
                        <initial-frame>0</initial-frame>
                        <collisions>Enabled</collisions>
                    </properties>
                    <blend-mode>0</blend-mode>
                    <effect-fallback>0</effect-fallback>
                    <world>
                        <x>960</x>
                        <y>600</y>
                        <z>0</z>
                        <width>1920</width>
                        <height>1200</height>
                        <depth>0</depth>
                        <hotspotX>0.5</hotspotX>
                        <hotspotY>0.5</hotspotY>
                        <angle>0</angle>
                        <opacity>1</opacity>
                    </world>
                </instance>
                <instance type="M7_End_BG" uid="1188">
                    <properties>
                        <initial-visibility>Visible</initial-visibility>
                        <initial-animation>Default</initial-animation>
                        <initial-frame>0</initial-frame>
                        <collisions>Enabled</collisions>
                    </properties>
                    <blend-mode>0</blend-mode>
                    <effect-fallback>0</effect-fallback>
                    <world>
                        <x>960</x>
                        <y>600</y>
                        <z>0</z>
                        <width>1200</width>
                        <height>840</height>
                        <depth>0</depth>
                        <hotspotX>0.5</hotspotX>
                        <hotspotY>0.5</hotspotY>
                        <angle>0</angle>
                        <opacity>1</opacity>
                    </world>
                </instance>
                <instance type="M7_End_Exit" uid="1189">
                    <properties>
                        <initial-visibility>Visible</initial-visibility>
                        <initial-animation>Default</initial-animation>
                        <initial-frame>0</initial-frame>
                        <collisions>Enabled</collisions>
                    </properties>
                    <blend-mode>0</blend-mode>
                    <effect-fallback>0</effect-fallback>
                    <world>
                        <x>660</x>
                        <y>800</y>
                        <z>0</z>
                        <width>240</width>
                        <height>240</height>
                        <depth>0</depth>
                        <hotspotX>0.5</hotspotX>
                        <hotspotY>0.5</hotspotY>
                        <angle>0</angle>
                        <opacity>1</opacity>
                    </world>
                </instance>
                <instance type="M7_End_Restart" uid="1190">
                    <properties>
                        <initial-visibility>Visible</initial-visibility>
                        <initial-animation>Default</initial-animation>
                        <initial-frame>0</initial-frame>
                        <collisions>Enabled</collisions>
                    </properties>
                    <blend-mode>0</blend-mode>
                    <effect-fallback>0</effect-fallback>
                    <world>
                        <x>1260</x>
                        <y>800</y>
                        <z>0</z>
                        <width>240</width>
                        <height>240</height>
                        <depth>0</depth>
                        <hotspotX>0.5</hotspotX>
                        <hotspotY>0.5</hotspotY>
                        <angle>0</angle>
                        <opacity>1</opacity>
                    </world>
                </instance>
                <instance type="M7_End_Text" uid="280">
                    <properties>
                        <text></text>
                        <initial-visibility>Visible</initial-visibility>
                        <font>Arial,-48,400,0</font>
                        <color>0,0,0</color>
                        <horizontal-alignment>Center</horizontal-alignment>
                        <vertical-alignment>Center</vertical-alignment>
                        <hotspot>Center</hotspot>
                        <wrapping>Word</wrapping>
                        <line-height>0</line-height>
                    </properties>
                    <blend-mode>0</blend-mode>
                    <effect-fallback>0</effect-fallback>
                    <world>
                        <x>960</x>
                        <y>600</y>
                        <z>0</z>
                        <width>741.882385254</width>
                        <height>166.441467285</height>
                        <depth>0</depth>
                        <hotspotX>0.5</hotspotX>
                        <hotspotY>0.5</hotspotY>
                        <angle>0</angle>
                        <opacity>1</opacity>
                    </world>
                </instance>
            </instances>
            <effects />
        </layer>
        <layer name="UI" sid="342928311930432">
            <initially-visible>1</initially-visible>
            <background-color>255,255,255</background-color>
            <transparent>1</transparent>
            <parallax>
                <x>1</x>
                <y>1</y>
            </parallax>
            <zoom-rate>1</zoom-rate>
            <opacity>1</opacity>
            <force-own-texture>0</force-own-texture>
            <global>0</global>
            <use-render-cells>0</use-render-cells>
            <blend-mode>0</blend-mode>
            <effect-fallback>0</effect-fallback>
            <instances>
                <instance type="M7_Timer_Bar" uid="1184">
                    <properties>
                        <initial-visibility>Visible</initial-visibility>
                        <initial-animation>Default</initial-animation>
                        <initial-frame>0</initial-frame>
                        <collisions>Enabled</collisions>
                    </properties>
                    <instance-variables>
                        <TimeLeft>0</TimeLeft>
                        <MaxWidth>1920</MaxWidth>
                    </instance-variables>
                    <blend-mode>0</blend-mode>
                    <effect-fallback>0</effect-fallback>
                    <world>
                        <x>960</x>
                        <y>26</y>
                        <z>0</z>
                        <width>1920</width>
                        <height>50</height>
                        <depth>0</depth>
                        <hotspotX>0.5</hotspotX>
                        <hotspotY>0.5</hotspotY>
                        <angle>0</angle>
                        <opacity>1</opacity>
                    </world>
                </instance>
                <instance type="M7_Timer_Icon" uid="2307">
                    <properties>
                        <initial-visibility>Visible</initial-visibility>
                        <initial-animation>Default</initial-animation>
                        <initial-frame>0</initial-frame>
                        <collisions>Enabled</collisions>
                    </properties>
                    <blend-mode>0</blend-mode>
                    <effect-fallback>0</effect-fallback>
                    <world>
                        <x>960</x>
                        <y>34</y>
                        <z>0</z>
                        <width>62</width>
                        <height>62</height>
                        <depth>0</depth>
                        <hotspotX>0.5</hotspotX>
                        <hotspotY>0.5</hotspotY>
                        <angle>0</angle>
                        <opacity>1</opacity>
                    </world>
                </instance>
                <instance type="M7_TemperatureText" uid="1186">
                    <properties>
                        <character-width>16</character-width>
                        <character-height>16</character-height>
                        <character-set>ABCDEFGHIJKLMNOPQRSTUVWXYZabcdefghijklmnopqrstuvwxyz0123456789.,;:?!-_~#&quot;&apos;&amp;()[]|`\/@°+=*$£€&lt;&gt;</character-set>
                        <text>18</text>
                        <scale>4</scale>
                        <initial-visibility>Visible</initial-visibility>
                        <horizontal-alignment>Right</horizontal-alignment>
                        <vertical-alignment>Center</vertical-alignment>
                        <hotspot>Center</hotspot>
                        <wrapping>Word</wrapping>
                        <character-spacing>0</character-spacing>
                        <line-height>0</line-height>
                    </properties>
                    <blend-mode>0</blend-mode>
                    <effect-fallback>0</effect-fallback>
                    <world>
                        <x>71</x>
                        <y>177</y>
                        <z>0</z>
                        <width>455.335174561</width>
                        <height>274.476501465</height>
                        <depth>0</depth>
                        <hotspotX>0.5</hotspotX>
                        <hotspotY>0.5</hotspotY>
                        <angle>0</angle>
                        <opacity>1</opacity>
                    </world>
                </instance>
                <instance type="M7_End_Star0" uid="1192">
                    <properties>
                        <initial-visibility>Visible</initial-visibility>
                        <initial-animation>Default</initial-animation>
                        <initial-frame>0</initial-frame>
                        <collisions>Enabled</collisions>
                    </properties>
                    <blend-mode>0</blend-mode>
                    <effect-fallback>0</effect-fallback>
                    <world>
                        <x>105</x>
                        <y>295</y>
                        <z>0</z>
                        <width>100</width>
                        <height>100</height>
                        <depth>0</depth>
                        <hotspotX>0.5</hotspotX>
                        <hotspotY>0.5</hotspotY>
                        <angle>0</angle>
                        <opacity>1</opacity>
                    </world>
                </instance>
                <instance type="M7_End_Star1" uid="1191">
                    <properties>
                        <initial-visibility>Visible</initial-visibility>
                        <initial-animation>Default</initial-animation>
                        <initial-frame>0</initial-frame>
                        <collisions>Enabled</collisions>
                    </properties>
                    <blend-mode>0</blend-mode>
                    <effect-fallback>0</effect-fallback>
                    <world>
                        <x>209</x>
                        <y>295</y>
                        <z>0</z>
                        <width>100</width>
                        <height>100</height>
                        <depth>0</depth>
                        <hotspotX>0.5</hotspotX>
                        <hotspotY>0.5</hotspotY>
                        <angle>0</angle>
                        <opacity>1</opacity>
                    </world>
                </instance>
                <instance type="M7_End_Star2" uid="1193">
                    <properties>
                        <initial-visibility>Visible</initial-visibility>
                        <initial-animation>Default</initial-animation>
                        <initial-frame>0</initial-frame>
                        <collisions>Enabled</collisions>
                    </properties>
                    <blend-mode>0</blend-mode>
                    <effect-fallback>0</effect-fallback>
                    <world>
                        <x>310</x>
                        <y>295</y>
                        <z>0</z>
                        <width>100</width>
                        <height>100</height>
                        <depth>0</depth>
                        <hotspotX>0.5</hotspotX>
                        <hotspotY>0.5</hotspotY>
                        <angle>0</angle>
                        <opacity>1</opacity>
                    </world>
                </instance>
            </instances>
            <effects />
        </layer>
        <layer name="Tutorial" sid="390761353574383">
            <initially-visible>1</initially-visible>
            <background-color>255,255,255</background-color>
            <transparent>1</transparent>
            <parallax>
                <x>1</x>
                <y>1</y>
            </parallax>
            <zoom-rate>1</zoom-rate>
            <opacity>1</opacity>
            <force-own-texture>1</force-own-texture>
            <global>0</global>
            <use-render-cells>0</use-render-cells>
            <blend-mode>0</blend-mode>
            <effect-fallback>0</effect-fallback>
            <instances>
                <instance type="M7_Tutorial_Highlight" uid="1194">
                    <properties>
                        <initial-visibility>Visible</initial-visibility>
                        <initial-animation>Default</initial-animation>
                        <initial-frame>0</initial-frame>
                        <collisions>Enabled</collisions>
                    </properties>
                    <blend-mode>0</blend-mode>
                    <effect-fallback>0</effect-fallback>
                    <world>
                        <x>446</x>
                        <y>536</y>
                        <z>0</z>
                        <width>3840</width>
                        <height>2400</height>
                        <depth>0</depth>
                        <hotspotX>0.5</hotspotX>
                        <hotspotY>0.5</hotspotY>
                        <angle>0</angle>
                        <opacity>1</opacity>
                    </world>
                </instance>
                <instance type="M7_Tutorial_Instructions" uid="1195">
                    <properties>
                        <text>Text</text>
                        <initial-visibility>Visible</initial-visibility>
                        <font>Arial,-96,400,0</font>
                        <color>255,255,255</color>
                        <horizontal-alignment>Center</horizontal-alignment>
                        <vertical-alignment>Bottom</vertical-alignment>
                        <hotspot>Top</hotspot>
                        <wrapping>Word</wrapping>
                        <line-height>0</line-height>
                    </properties>
                    <blend-mode>0</blend-mode>
                    <effect-fallback>0</effect-fallback>
                    <world>
                        <x>960</x>
                        <y>646</y>
                        <z>0</z>
                        <width>1600</width>
                        <height>354</height>
                        <depth>0</depth>
                        <hotspotX>0.5</hotspotX>
                        <hotspotY>0</hotspotY>
                        <angle>0</angle>
                        <opacity>1</opacity>
                    </world>
                </instance>
                <instance type="M7_Tutorial_Prompt" uid="1196">
                    <properties>
                        <text>Text</text>
                        <initial-visibility>Visible</initial-visibility>
                        <font>Arial,-64,400,0</font>
                        <color>255,255,255</color>
                        <horizontal-alignment>Center</horizontal-alignment>
                        <vertical-alignment>Bottom</vertical-alignment>
                        <hotspot>Bottom</hotspot>
                        <wrapping>Word</wrapping>
                        <line-height>0</line-height>
                    </properties>
                    <blend-mode>0</blend-mode>
                    <effect-fallback>0</effect-fallback>
                    <world>
                        <x>960</x>
                        <y>1150</y>
                        <z>0</z>
                        <width>1500</width>
                        <height>200</height>
                        <depth>0</depth>
                        <hotspotX>0.5</hotspotX>
                        <hotspotY>1</hotspotY>
                        <angle>0</angle>
                        <opacity>1</opacity>
                    </world>
                </instance>
            </instances>
            <effects />
        </layer>
    </layers>
    <nonworld-instances>
        <instance type="GG_State" uid="1203" />
    </nonworld-instances>
    <effects />
</c2layout>
