<?xml version="1.0" encoding="utf-8" ?>
<c2layout>
    <name>m2_2_main</name>
    <sid>279320739909599</sid>
    <event-sheet>m2_2_main</event-sheet>
    <size>
        <width>2500</width>
        <height>1500</height>
    </size>
    <margins>
        <horizontal>500</horizontal>
        <vertical>500</vertical>
    </margins>
    <unbounded-scrolling>0</unbounded-scrolling>
    <layers>
        <layer name="Layer 0" sid="604348839235566">
            <initially-visible>1</initially-visible>
            <background-color>255,255,255</background-color>
            <transparent>0</transparent>
            <parallax>
                <x>1</x>
                <y>1</y>
            </parallax>
            <zoom-rate>1</zoom-rate>
            <opacity>1</opacity>
            <force-own-texture>0</force-own-texture>
            <global>0</global>
            <use-render-cells>0</use-render-cells>
            <blend-mode>0</blend-mode>
            <effect-fallback>0</effect-fallback>
            <instances>
                <instance type="m2_2_BG" uid="4">
                    <properties>
                        <initial-visibility>Visible</initial-visibility>
                        <initial-animation>Default</initial-animation>
                        <initial-frame>0</initial-frame>
                        <collisions>Enabled</collisions>
                    </properties>
                    <blend-mode>0</blend-mode>
                    <effect-fallback>0</effect-fallback>
                    <world>
                        <x>960</x>
                        <y>600</y>
                        <z>0</z>
                        <width>1920</width>
                        <height>1200</height>
                        <depth>0</depth>
                        <hotspotX>0.5</hotspotX>
                        <hotspotY>0.5</hotspotY>
                        <angle>0</angle>
                        <opacity>1</opacity>
                    </world>
                </instance>
                <instance type="m2_2_hook" uid="33">
                    <properties>
                        <initial-visibility>Visible</initial-visibility>
                        <initial-animation>Default</initial-animation>
                        <initial-frame>0</initial-frame>
                        <collisions>Enabled</collisions>
                    </properties>
                    <blend-mode>0</blend-mode>
                    <effect-fallback>0</effect-fallback>
                    <world>
                        <x>503.957489014</x>
                        <y>393.19821167</y>
                        <z>0</z>
                        <width>10</width>
                        <height>40</height>
                        <depth>0</depth>
                        <hotspotX>0.5</hotspotX>
                        <hotspotY>0.5</hotspotY>
                        <angle>0</angle>
                        <opacity>1</opacity>
                    </world>
                </instance>
                <instance type="m2_2_topCabinet" uid="8">
                    <properties>
                        <initial-visibility>Visible</initial-visibility>
                        <initial-animation>Default</initial-animation>
                        <initial-frame>0</initial-frame>
                        <collisions>Enabled</collisions>
                    </properties>
                    <blend-mode>0</blend-mode>
                    <effect-fallback>0</effect-fallback>
                    <world>
                        <x>695</x>
                        <y>173</y>
                        <z>0</z>
                        <width>550</width>
                        <height>350</height>
                        <depth>0</depth>
                        <hotspotX>0.5</hotspotX>
                        <hotspotY>0.5</hotspotY>
                        <angle>0</angle>
                        <opacity>1</opacity>
                    </world>
                </instance>
                <instance type="m2_2_plugHole" uid="31">
                    <properties>
                        <initial-visibility>Visible</initial-visibility>
                        <initial-animation>Default</initial-animation>
                        <initial-frame>0</initial-frame>
                        <collisions>Enabled</collisions>
                    </properties>
                    <blend-mode>0</blend-mode>
                    <effect-fallback>0</effect-fallback>
                    <world>
                        <x>826.906433105</x>
                        <y>518.557128906</y>
                        <z>0</z>
                        <width>50</width>
                        <height>100</height>
                        <depth>0</depth>
                        <hotspotX>0.5</hotspotX>
                        <hotspotY>0.5</hotspotY>
                        <angle>0</angle>
                        <opacity>1</opacity>
                    </world>
                </instance>
                <instance type="m2_2_toasterWire" uid="41">
                    <properties>
                        <initial-visibility>Visible</initial-visibility>
                        <initial-animation>Default</initial-animation>
                        <initial-frame>0</initial-frame>
                        <collisions>Enabled</collisions>
                    </properties>
                    <instance-variables>
                        <number>0</number>
                    </instance-variables>
                    <behavior-instances>
                        <behavior-instance type="Physics">
                            <properties>
                                <immovable>No</immovable>
                                <collision-mask>Use collision polygon</collision-mask>
                                <prevent-rotation>No</prevent-rotation>
                                <density>1</density>
                                <friction>0.5</friction>
                                <elasticity>0.2</elasticity>
                                <linear-damping>0</linear-damping>
                                <angular-damping>0.01</angular-damping>
                                <bullet>No</bullet>
                                <initial-state>Enabled</initial-state>
                            </properties>
                        </behavior-instance>
                    </behavior-instances>
                    <blend-mode>0</blend-mode>
                    <effect-fallback>0</effect-fallback>
                    <world>
                        <x>830</x>
                        <y>535</y>
                        <z>0</z>
                        <width>15</width>
                        <height>15</height>
                        <depth>0</depth>
                        <hotspotX>0.5</hotspotX>
                        <hotspotY>0.5</hotspotY>
                        <angle>0</angle>
                        <opacity>1</opacity>
                    </world>
                </instance>
                <instance type="m2_2_microwavePlughole" uid="37">
                    <properties>
                        <initial-visibility>Visible</initial-visibility>
                        <initial-animation>Default</initial-animation>
                        <initial-frame>0</initial-frame>
                        <collisions>Enabled</collisions>
                    </properties>
                    <blend-mode>0</blend-mode>
                    <effect-fallback>0</effect-fallback>
                    <world>
                        <x>827</x>
                        <y>485</y>
                        <z>0</z>
                        <width>52</width>
                        <height>53</height>
                        <depth>0</depth>
                        <hotspotX>0.5</hotspotX>
                        <hotspotY>0.96226418</hotspotY>
                        <angle>0</angle>
                        <opacity>1</opacity>
                    </world>
                </instance>
                <instance type="m2_2_microwaveWire" uid="44">
                    <properties>
                        <initial-visibility>Visible</initial-visibility>
                        <initial-animation>Default</initial-animation>
                        <initial-frame>0</initial-frame>
                        <collisions>Enabled</collisions>
                    </properties>
                    <instance-variables>
                        <number>0</number>
                    </instance-variables>
                    <behavior-instances>
                        <behavior-instance type="Physics">
                            <properties>
                                <immovable>No</immovable>
                                <collision-mask>Use collision polygon</collision-mask>
                                <prevent-rotation>No</prevent-rotation>
                                <density>1</density>
                                <friction>0.5</friction>
                                <elasticity>0.2</elasticity>
                                <linear-damping>0</linear-damping>
                                <angular-damping>0.01</angular-damping>
                                <bullet>No</bullet>
                                <initial-state>Enabled</initial-state>
                            </properties>
                        </behavior-instance>
                    </behavior-instances>
                    <blend-mode>0</blend-mode>
                    <effect-fallback>0</effect-fallback>
                    <world>
                        <x>830</x>
                        <y>465</y>
                        <z>0</z>
                        <width>15</width>
                        <height>15</height>
                        <depth>0</depth>
                        <hotspotX>0.5</hotspotX>
                        <hotspotY>0.5</hotspotY>
                        <angle>1.570796371</angle>
                        <opacity>1</opacity>
                    </world>
                </instance>
                <instance type="m2_2_microwavePlug" uid="40">
                    <properties>
                        <initial-visibility>Visible</initial-visibility>
                        <initial-animation>Default</initial-animation>
                        <initial-frame>0</initial-frame>
                        <collisions>Enabled</collisions>
                    </properties>
                    <behavior-instances>
                        <behavior-instance type="Physics">
                            <properties>
                                <immovable>Yes</immovable>
                                <collision-mask>Use collision polygon</collision-mask>
                                <prevent-rotation>No</prevent-rotation>
                                <density>1</density>
                                <friction>0.5</friction>
                                <elasticity>0.2</elasticity>
                                <linear-damping>0</linear-damping>
                                <angular-damping>0.01</angular-damping>
                                <bullet>No</bullet>
                                <initial-state>Enabled</initial-state>
                            </properties>
                        </behavior-instance>
                    </behavior-instances>
                    <blend-mode>0</blend-mode>
                    <effect-fallback>0</effect-fallback>
                    <world>
                        <x>830</x>
                        <y>465</y>
                        <z>0</z>
                        <width>67.5</width>
                        <height>67.5</height>
                        <depth>0</depth>
                        <hotspotX>0.5</hotspotX>
                        <hotspotY>0.5</hotspotY>
                        <angle>3.141592741</angle>
                        <opacity>1</opacity>
                    </world>
                </instance>
                <instance type="m2_2_covfefeWire" uid="42">
                    <properties>
                        <initial-visibility>Visible</initial-visibility>
                        <initial-animation>Default</initial-animation>
                        <initial-frame>0</initial-frame>
                        <collisions>Enabled</collisions>
                    </properties>
                    <instance-variables>
                        <number>0</number>
                    </instance-variables>
                    <behavior-instances>
                        <behavior-instance type="Physics">
                            <properties>
                                <immovable>No</immovable>
                                <collision-mask>Use collision polygon</collision-mask>
                                <prevent-rotation>No</prevent-rotation>
                                <density>1</density>
                                <friction>0.5</friction>
                                <elasticity>0.2</elasticity>
                                <linear-damping>0</linear-damping>
                                <angular-damping>0.01</angular-damping>
                                <bullet>No</bullet>
                                <initial-state>Enabled</initial-state>
                            </properties>
                        </behavior-instance>
                    </behavior-instances>
                    <blend-mode>0</blend-mode>
                    <effect-fallback>0</effect-fallback>
                    <world>
                        <x>830</x>
                        <y>500</y>
                        <z>0</z>
                        <width>15</width>
                        <height>15</height>
                        <depth>0</depth>
                        <hotspotX>0.5</hotspotX>
                        <hotspotY>0.5</hotspotY>
                        <angle>0</angle>
                        <opacity>1</opacity>
                    </world>
                </instance>
                <instance type="m2_2_covfefePlug" uid="39">
                    <properties>
                        <initial-visibility>Visible</initial-visibility>
                        <initial-animation>Default</initial-animation>
                        <initial-frame>0</initial-frame>
                        <collisions>Enabled</collisions>
                    </properties>
                    <behavior-instances>
                        <behavior-instance type="Physics">
                            <properties>
                                <immovable>Yes</immovable>
                                <collision-mask>Use collision polygon</collision-mask>
                                <prevent-rotation>No</prevent-rotation>
                                <density>1</density>
                                <friction>0.5</friction>
                                <elasticity>0.2</elasticity>
                                <linear-damping>0</linear-damping>
                                <angular-damping>0.01</angular-damping>
                                <bullet>No</bullet>
                                <initial-state>Enabled</initial-state>
                            </properties>
                        </behavior-instance>
                    </behavior-instances>
                    <blend-mode>0</blend-mode>
                    <effect-fallback>0</effect-fallback>
                    <world>
                        <x>830</x>
                        <y>500</y>
                        <z>0</z>
                        <width>67.5</width>
                        <height>67.5</height>
                        <depth>0</depth>
                        <hotspotX>0.5</hotspotX>
                        <hotspotY>0.5</hotspotY>
                        <angle>0</angle>
                        <opacity>1</opacity>
                    </world>
                </instance>
                <instance type="m2_2_toasterPlug" uid="38">
                    <properties>
                        <initial-visibility>Visible</initial-visibility>
                        <initial-animation>Default</initial-animation>
                        <initial-frame>0</initial-frame>
                        <collisions>Enabled</collisions>
                    </properties>
                    <behavior-instances>
                        <behavior-instance type="Physics">
                            <properties>
                                <immovable>Yes</immovable>
                                <collision-mask>Use collision polygon</collision-mask>
                                <prevent-rotation>No</prevent-rotation>
                                <density>1</density>
                                <friction>0.5</friction>
                                <elasticity>0.2</elasticity>
                                <linear-damping>0</linear-damping>
                                <angular-damping>0.01</angular-damping>
                                <bullet>No</bullet>
                                <initial-state>Enabled</initial-state>
                            </properties>
                        </behavior-instance>
                    </behavior-instances>
                    <blend-mode>0</blend-mode>
                    <effect-fallback>0</effect-fallback>
                    <world>
                        <x>830</x>
                        <y>535</y>
                        <z>0</z>
                        <width>67.5</width>
                        <height>67.5</height>
                        <depth>0</depth>
                        <hotspotX>0.5</hotspotX>
                        <hotspotY>0.5</hotspotY>
                        <angle>0</angle>
                        <opacity>1</opacity>
                    </world>
                </instance>
                <instance type="m2_2_toaster" uid="30">
                    <properties>
                        <initial-visibility>Visible</initial-visibility>
                        <initial-animation>Default</initial-animation>
                        <initial-frame>0</initial-frame>
                        <collisions>Enabled</collisions>
                    </properties>
                    <instance-variables>
                        <power>true</power>
                    </instance-variables>
                    <behavior-instances>
                        <behavior-instance type="Physics">
                            <properties>
                                <immovable>Yes</immovable>
                                <collision-mask>Use collision polygon</collision-mask>
                                <prevent-rotation>Yes</prevent-rotation>
                                <density>1</density>
                                <friction>1</friction>
                                <elasticity>0</elasticity>
                                <linear-damping>0</linear-damping>
                                <angular-damping>0.01</angular-damping>
                                <bullet>No</bullet>
                                <initial-state>Enabled</initial-state>
                            </properties>
                        </behavior-instance>
                        <behavior-instance type="DragDrop">
                            <properties>
                                <axes>Horizontal only</axes>
                                <initial-state>Enabled</initial-state>
                            </properties>
                        </behavior-instance>
                    </behavior-instances>
                    <blend-mode>0</blend-mode>
                    <effect-fallback>0</effect-fallback>
                    <world>
                        <x>780</x>
                        <y>550</y>
                        <z>0</z>
                        <width>80</width>
                        <height>120</height>
                        <depth>0</depth>
                        <hotspotX>0.5</hotspotX>
                        <hotspotY>0.5</hotspotY>
                        <angle>0</angle>
                        <opacity>1</opacity>
                    </world>
                </instance>
                <instance type="m2_2_coffeeMaker" uid="32">
                    <properties>
                        <initial-visibility>Visible</initial-visibility>
                        <initial-animation>Default</initial-animation>
                        <initial-frame>0</initial-frame>
                        <collisions>Enabled</collisions>
                    </properties>
                    <instance-variables>
                        <power>true</power>
                    </instance-variables>
                    <behavior-instances>
                        <behavior-instance type="Physics">
                            <properties>
                                <immovable>Yes</immovable>
                                <collision-mask>Use collision polygon</collision-mask>
                                <prevent-rotation>Yes</prevent-rotation>
                                <density>1</density>
                                <friction>1</friction>
                                <elasticity>0</elasticity>
                                <linear-damping>0</linear-damping>
                                <angular-damping>0.01</angular-damping>
                                <bullet>No</bullet>
                                <initial-state>Enabled</initial-state>
                            </properties>
                        </behavior-instance>
                        <behavior-instance type="DragDrop">
                            <properties>
                                <axes>Horizontal only</axes>
                                <initial-state>Enabled</initial-state>
                            </properties>
                        </behavior-instance>
                    </behavior-instances>
                    <blend-mode>0</blend-mode>
                    <effect-fallback>0</effect-fallback>
                    <world>
                        <x>900</x>
                        <y>510</y>
                        <z>0</z>
                        <width>120</width>
                        <height>200</height>
                        <depth>0</depth>
                        <hotspotX>0.5</hotspotX>
                        <hotspotY>0.5</hotspotY>
                        <angle>0</angle>
                        <opacity>1</opacity>
                    </world>
                </instance>
                <instance type="m2_2_Door" uid="34">
                    <properties>
                        <initial-visibility>Visible</initial-visibility>
                        <initial-animation>Default</initial-animation>
                        <initial-frame>0</initial-frame>
                        <collisions>Enabled</collisions>
                    </properties>
                    <behavior-instances>
                        <behavior-instance type="Physics">
                            <properties>
                                <immovable>Yes</immovable>
                                <collision-mask>Use collision polygon</collision-mask>
                                <prevent-rotation>No</prevent-rotation>
                                <density>1</density>
                                <friction>0.5</friction>
                                <elasticity>0.2</elasticity>
                                <linear-damping>0</linear-damping>
                                <angular-damping>0.01</angular-damping>
                                <bullet>No</bullet>
                                <initial-state>Enabled</initial-state>
                            </properties>
                        </behavior-instance>
                    </behavior-instances>
                    <blend-mode>0</blend-mode>
                    <effect-fallback>0</effect-fallback>
                    <world>
                        <x>260</x>
                        <y>680</y>
                        <z>0</z>
                        <width>320</width>
                        <height>700</height>
                        <depth>0</depth>
                        <hotspotX>0.5</hotspotX>
                        <hotspotY>0.5</hotspotY>
                        <angle>0</angle>
                        <opacity>1</opacity>
                    </world>
                </instance>
                <instance type="m2_2_valve" uid="35">
                    <properties>
                        <initial-visibility>Visible</initial-visibility>
                        <initial-animation>Default</initial-animation>
                        <initial-frame>0</initial-frame>
                        <collisions>Enabled</collisions>
                    </properties>
                    <blend-mode>0</blend-mode>
                    <effect-fallback>0</effect-fallback>
                    <world>
                        <x>675.538085938</x>
                        <y>787.422424316</y>
                        <z>0</z>
                        <width>50</width>
                        <height>30</height>
                        <depth>0</depth>
                        <hotspotX>0.5</hotspotX>
                        <hotspotY>0.5</hotspotY>
                        <angle>0</angle>
                        <opacity>1</opacity>
                    </world>
                </instance>
                <instance type="m2_2_waterDroplet" uid="36">
                    <properties>
                        <initial-visibility>Visible</initial-visibility>
                        <initial-animation>Default</initial-animation>
                        <initial-frame>0</initial-frame>
                        <collisions>Enabled</collisions>
                    </properties>
                    <behavior-instances>
                        <behavior-instance type="Physics">
                            <properties>
                                <immovable>No</immovable>
                                <collision-mask>Use collision polygon</collision-mask>
                                <prevent-rotation>No</prevent-rotation>
                                <density>1</density>
                                <friction>0.5</friction>
                                <elasticity>0.2</elasticity>
                                <linear-damping>0</linear-damping>
                                <angular-damping>0.01</angular-damping>
                                <bullet>No</bullet>
                                <initial-state>Enabled</initial-state>
                            </properties>
                        </behavior-instance>
                    </behavior-instances>
                    <blend-mode>0</blend-mode>
                    <effect-fallback>0</effect-fallback>
                    <world>
                        <x>9001</x>
                        <y>531.104003906</y>
                        <z>0</z>
                        <width>20</width>
                        <height>34</height>
                        <depth>0</depth>
                        <hotspotX>0.5</hotspotX>
                        <hotspotY>0.5</hotspotY>
                        <angle>0</angle>
                        <opacity>1</opacity>
                    </world>
                </instance>
                <instance type="m2_2_waterFaucet" uid="43">
                    <properties>
                        <initial-visibility>Visible</initial-visibility>
                        <initial-animation>Default</initial-animation>
                        <initial-frame>0</initial-frame>
                        <collisions>Enabled</collisions>
                    </properties>
                    <instance-variables>
                        <key>false</key>
                        <open>false</open>
                    </instance-variables>
                    <behavior-instances>
                        <behavior-instance type="Physics">
                            <properties>
                                <immovable>Yes</immovable>
                                <collision-mask>Use collision polygon</collision-mask>
                                <prevent-rotation>No</prevent-rotation>
                                <density>1</density>
                                <friction>0.5</friction>
                                <elasticity>0.2</elasticity>
                                <linear-damping>0</linear-damping>
                                <angular-damping>0.01</angular-damping>
                                <bullet>No</bullet>
                                <initial-state>Enabled</initial-state>
                            </properties>
                        </behavior-instance>
                    </behavior-instances>
                    <blend-mode>0</blend-mode>
                    <effect-fallback>0</effect-fallback>
                    <world>
                        <x>595</x>
                        <y>830</y>
                        <z>0</z>
                        <width>350</width>
                        <height>400</height>
                        <depth>0</depth>
                        <hotspotX>0.5</hotspotX>
                        <hotspotY>0.5</hotspotY>
                        <angle>0</angle>
                        <opacity>1</opacity>
                    </world>
                </instance>
                <instance type="m2_2_stove" uid="45">
                    <properties>
                        <initial-visibility>Visible</initial-visibility>
                        <initial-animation>Default</initial-animation>
                        <initial-frame>0</initial-frame>
                        <collisions>Enabled</collisions>
                    </properties>
                    <behavior-instances>
                        <behavior-instance type="Physics">
                            <properties>
                                <immovable>Yes</immovable>
                                <collision-mask>Use collision polygon</collision-mask>
                                <prevent-rotation>No</prevent-rotation>
                                <density>1</density>
                                <friction>0.5</friction>
                                <elasticity>0.2</elasticity>
                                <linear-damping>0</linear-damping>
                                <angular-damping>0.01</angular-damping>
                                <bullet>No</bullet>
                                <initial-state>Enabled</initial-state>
                            </properties>
                        </behavior-instance>
                    </behavior-instances>
                    <blend-mode>0</blend-mode>
                    <effect-fallback>0</effect-fallback>
                    <world>
                        <x>1195</x>
                        <y>820</y>
                        <z>0</z>
                        <width>450</width>
                        <height>420</height>
                        <depth>0</depth>
                        <hotspotX>0.5</hotspotX>
                        <hotspotY>0.5</hotspotY>
                        <angle>0</angle>
                        <opacity>1</opacity>
                    </world>
                </instance>
                <instance type="m2_2_uselessShit1" uid="46">
                    <properties>
                        <initial-visibility>Visible</initial-visibility>
                        <initial-animation>Default</initial-animation>
                        <initial-frame>0</initial-frame>
                        <collisions>Enabled</collisions>
                    </properties>
                    <instance-variables>
                        <open>false</open>
                    </instance-variables>
                    <blend-mode>0</blend-mode>
                    <effect-fallback>0</effect-fallback>
                    <world>
                        <x>870</x>
                        <y>830</y>
                        <z>0</z>
                        <width>200</width>
                        <height>400</height>
                        <depth>0</depth>
                        <hotspotX>0.5</hotspotX>
                        <hotspotY>0.5</hotspotY>
                        <angle>0</angle>
                        <opacity>1</opacity>
                    </world>
                </instance>
                <instance type="m2_2_Lights" uid="47">
                    <properties>
                        <initial-visibility>Visible</initial-visibility>
                        <initial-animation>Default</initial-animation>
                        <initial-frame>0</initial-frame>
                        <collisions>Enabled</collisions>
                    </properties>
                    <instance-variables>
                        <power>false</power>
                    </instance-variables>
                    <blend-mode>0</blend-mode>
                    <effect-fallback>0</effect-fallback>
                    <world>
                        <x>1868</x>
                        <y>430</y>
                        <z>0</z>
                        <width>50</width>
                        <height>100</height>
                        <depth>0</depth>
                        <hotspotX>0.5</hotspotX>
                        <hotspotY>0.5</hotspotY>
                        <angle>0</angle>
                        <opacity>1</opacity>
                    </world>
                </instance>
                <instance type="m2_2_stoveLight" uid="48">
                    <properties>
                        <initial-visibility>Visible</initial-visibility>
                        <initial-animation>Default</initial-animation>
                        <initial-frame>0</initial-frame>
                        <collisions>Enabled</collisions>
                    </properties>
                    <instance-variables>
                        <power>false</power>
                        <open>0</open>
                    </instance-variables>
                    <blend-mode>0</blend-mode>
                    <effect-fallback>0</effect-fallback>
                    <world>
                        <x>1195</x>
                        <y>150</y>
                        <z>0</z>
                        <width>450</width>
                        <height>300</height>
                        <depth>0</depth>
                        <hotspotX>0.5</hotspotX>
                        <hotspotY>0.5</hotspotY>
                        <angle>0</angle>
                        <opacity>1</opacity>
                    </world>
                </instance>
                <instance type="m2_2_microwave" uid="49">
                    <properties>
                        <initial-visibility>Visible</initial-visibility>
                        <initial-animation>Default</initial-animation>
                        <initial-frame>0</initial-frame>
                        <collisions>Enabled</collisions>
                    </properties>
                    <instance-variables>
                        <open>1</open>
                        <opens>true</opens>
                        <power>true</power>
                    </instance-variables>
                    <behavior-instances>
                        <behavior-instance type="Physics">
                            <properties>
                                <immovable>Yes</immovable>
                                <collision-mask>Use collision polygon</collision-mask>
                                <prevent-rotation>No</prevent-rotation>
                                <density>1</density>
                                <friction>0.5</friction>
                                <elasticity>0.2</elasticity>
                                <linear-damping>0</linear-damping>
                                <angular-damping>0.01</angular-damping>
                                <bullet>No</bullet>
                                <initial-state>Enabled</initial-state>
                            </properties>
                        </behavior-instance>
                    </behavior-instances>
                    <blend-mode>0</blend-mode>
                    <effect-fallback>0</effect-fallback>
                    <world>
                        <x>810</x>
                        <y>245</y>
                        <z>0</z>
                        <width>280</width>
                        <height>178</height>
                        <depth>0</depth>
                        <hotspotX>0.5</hotspotX>
                        <hotspotY>0.5</hotspotY>
                        <angle>0</angle>
                        <opacity>1</opacity>
                    </world>
                </instance>
                <instance type="m2_2_stoveLightLight" uid="50">
                    <properties>
                        <initial-visibility>Visible</initial-visibility>
                        <initial-animation>Default</initial-animation>
                        <initial-frame>0</initial-frame>
                        <collisions>Enabled</collisions>
                    </properties>
                    <blend-mode>0</blend-mode>
                    <effect-fallback>0</effect-fallback>
                    <world>
                        <x>1378</x>
                        <y>279</y>
                        <z>0</z>
                        <width>32</width>
                        <height>32</height>
                        <depth>0</depth>
                        <hotspotX>0.5</hotspotX>
                        <hotspotY>0.5</hotspotY>
                        <angle>0</angle>
                        <opacity>0</opacity>
                    </world>
                </instance>
                <instance type="m2_2_key" uid="51">
                    <properties>
                        <initial-visibility>Visible</initial-visibility>
                        <initial-animation>Default</initial-animation>
                        <initial-frame>0</initial-frame>
                        <collisions>Enabled</collisions>
                    </properties>
                    <blend-mode>0</blend-mode>
                    <effect-fallback>0</effect-fallback>
                    <world>
                        <x>504</x>
                        <y>414</y>
                        <z>0</z>
                        <width>60</width>
                        <height>120</height>
                        <depth>0</depth>
                        <hotspotX>0.5</hotspotX>
                        <hotspotY>0.5</hotspotY>
                        <angle>0</angle>
                        <opacity>1</opacity>
                    </world>
                </instance>
                <instance type="m2_2_actualFaucet" uid="52">
                    <properties>
                        <initial-visibility>Visible</initial-visibility>
                        <initial-animation>Default</initial-animation>
                        <initial-frame>0</initial-frame>
                        <collisions>Enabled</collisions>
                    </properties>
                    <instance-variables>
                        <water>true</water>
                    </instance-variables>
                    <behavior-instances>
                        <behavior-instance type="Physics">
                            <properties>
                                <immovable>Yes</immovable>
                                <collision-mask>Use collision polygon</collision-mask>
                                <prevent-rotation>No</prevent-rotation>
                                <density>1</density>
                                <friction>0.5</friction>
                                <elasticity>0.2</elasticity>
                                <linear-damping>0</linear-damping>
                                <angular-damping>0.01</angular-damping>
                                <bullet>No</bullet>
                                <initial-state>Enabled</initial-state>
                            </properties>
                        </behavior-instance>
                    </behavior-instances>
                    <blend-mode>0</blend-mode>
                    <effect-fallback>0</effect-fallback>
                    <world>
                        <x>695</x>
                        <y>555</y>
                        <z>0</z>
                        <width>550</width>
                        <height>150</height>
                        <depth>0</depth>
                        <hotspotX>0.5</hotspotX>
                        <hotspotY>0.5</hotspotY>
                        <angle>0</angle>
                        <opacity>1</opacity>
                    </world>
                </instance>
                <instance type="m2_2_fridgePlug" uid="53">
                    <properties>
                        <initial-visibility>Visible</initial-visibility>
                        <initial-animation>Default</initial-animation>
                        <initial-frame>0</initial-frame>
                        <collisions>Enabled</collisions>
                    </properties>
                    <blend-mode>0</blend-mode>
                    <effect-fallback>0</effect-fallback>
                    <world>
                        <x>1865</x>
                        <y>900</y>
                        <z>0</z>
                        <width>50</width>
                        <height>100</height>
                        <depth>0</depth>
                        <hotspotX>0.5</hotspotX>
                        <hotspotY>0.5</hotspotY>
                        <angle>0</angle>
                        <opacity>1</opacity>
                    </world>
                </instance>
                <instance type="m2_2_fridgeWire" uid="54">
                    <properties>
                        <initial-visibility>Visible</initial-visibility>
                        <initial-animation>Default</initial-animation>
                        <initial-frame>0</initial-frame>
                        <collisions>Enabled</collisions>
                    </properties>
                    <instance-variables>
                        <number>0</number>
                    </instance-variables>
                    <behavior-instances>
                        <behavior-instance type="Physics">
                            <properties>
                                <immovable>No</immovable>
                                <collision-mask>Use collision polygon</collision-mask>
                                <prevent-rotation>No</prevent-rotation>
                                <density>1</density>
                                <friction>0.5</friction>
                                <elasticity>0.2</elasticity>
                                <linear-damping>0</linear-damping>
                                <angular-damping>0.01</angular-damping>
                                <bullet>No</bullet>
                                <initial-state>Enabled</initial-state>
                            </properties>
                        </behavior-instance>
                    </behavior-instances>
                    <blend-mode>0</blend-mode>
                    <effect-fallback>0</effect-fallback>
                    <world>
                        <x>1865</x>
                        <y>885</y>
                        <z>0</z>
                        <width>15</width>
                        <height>15</height>
                        <depth>0</depth>
                        <hotspotX>0.5</hotspotX>
                        <hotspotY>0.5</hotspotY>
                        <angle>0.213839963</angle>
                        <opacity>1</opacity>
                    </world>
                </instance>
                <instance type="m2_2_fridge" uid="55">
                    <properties>
                        <initial-visibility>Visible</initial-visibility>
                        <initial-animation>Default</initial-animation>
                        <initial-frame>0</initial-frame>
                        <collisions>Enabled</collisions>
                    </properties>
                    <instance-variables>
                        <opens>false</opens>
                        <open>0</open>
                    </instance-variables>
                    <behavior-instances>
                        <behavior-instance type="Physics">
                            <properties>
                                <immovable>Yes</immovable>
                                <collision-mask>Use collision polygon</collision-mask>
                                <prevent-rotation>No</prevent-rotation>
                                <density>1</density>
                                <friction>0.5</friction>
                                <elasticity>0.2</elasticity>
                                <linear-damping>0</linear-damping>
                                <angular-damping>0.01</angular-damping>
                                <bullet>No</bullet>
                                <initial-state>Enabled</initial-state>
                            </properties>
                        </behavior-instance>
                    </behavior-instances>
                    <blend-mode>0</blend-mode>
                    <effect-fallback>0</effect-fallback>
                    <world>
                        <x>1620</x>
                        <y>620</y>
                        <z>0</z>
                        <width>400</width>
                        <height>820</height>
                        <depth>0</depth>
                        <hotspotX>0.5</hotspotX>
                        <hotspotY>0.5</hotspotY>
                        <angle>0</angle>
                        <opacity>1</opacity>
                    </world>
                </instance>
                <instance type="m2_2_fridgePlugThing" uid="56">
                    <properties>
                        <initial-visibility>Visible</initial-visibility>
                        <initial-animation>Default</initial-animation>
                        <initial-frame>0</initial-frame>
                        <collisions>Enabled</collisions>
                    </properties>
                    <behavior-instances>
                        <behavior-instance type="Physics">
                            <properties>
                                <immovable>Yes</immovable>
                                <collision-mask>Use collision polygon</collision-mask>
                                <prevent-rotation>No</prevent-rotation>
                                <density>1</density>
                                <friction>0.5</friction>
                                <elasticity>0.2</elasticity>
                                <linear-damping>0</linear-damping>
                                <angular-damping>0.01</angular-damping>
                                <bullet>No</bullet>
                                <initial-state>Enabled</initial-state>
                            </properties>
                        </behavior-instance>
                    </behavior-instances>
                    <blend-mode>0</blend-mode>
                    <effect-fallback>0</effect-fallback>
                    <world>
                        <x>1866.5</x>
                        <y>883</y>
                        <z>0</z>
                        <width>45</width>
                        <height>45</height>
                        <depth>0</depth>
                        <hotspotX>0.5</hotspotX>
                        <hotspotY>0.5</hotspotY>
                        <angle>0</angle>
                        <opacity>1</opacity>
                    </world>
                </instance>
                <instance type="m2_2_floor" uid="57">
                    <properties>
                        <initial-visibility>Invisible</initial-visibility>
                        <initial-animation>Default</initial-animation>
                        <initial-frame>0</initial-frame>
                        <collisions>Enabled</collisions>
                    </properties>
                    <behavior-instances>
                        <behavior-instance type="Physics">
                            <properties>
                                <immovable>Yes</immovable>
                                <collision-mask>Use collision polygon</collision-mask>
                                <prevent-rotation>No</prevent-rotation>
                                <density>1</density>
                                <friction>0.5</friction>
                                <elasticity>0.2</elasticity>
                                <linear-damping>0</linear-damping>
                                <angular-damping>0.01</angular-damping>
                                <bullet>No</bullet>
                                <initial-state>Enabled</initial-state>
                            </properties>
                        </behavior-instance>
                    </behavior-instances>
                    <blend-mode>0</blend-mode>
                    <effect-fallback>0</effect-fallback>
                    <world>
                        <x>960</x>
                        <y>1157</y>
                        <z>0</z>
                        <width>1920</width>
                        <height>250</height>
                        <depth>0</depth>
                        <hotspotX>0.5</hotspotX>
                        <hotspotY>0.5</hotspotY>
                        <angle>0</angle>
                        <opacity>1</opacity>
                    </world>
                </instance>
                <instance type="m2_2_microwaveLight" uid="61">
                    <properties>
                        <initial-visibility>Visible</initial-visibility>
                        <initial-animation>Default</initial-animation>
                        <initial-frame>0</initial-frame>
                        <collisions>Enabled</collisions>
                    </properties>
                    <blend-mode>0</blend-mode>
                    <effect-fallback>0</effect-fallback>
                    <world>
                        <x>940</x>
                        <y>170</y>
                        <z>0</z>
                        <width>14</width>
                        <height>14</height>
                        <depth>0</depth>
                        <hotspotX>0.5</hotspotX>
                        <hotspotY>0.5</hotspotY>
                        <angle>0</angle>
                        <opacity>1</opacity>
                    </world>
                </instance>
                <instance type="m2_2_toasterLight" uid="62">
                    <properties>
                        <initial-visibility>Visible</initial-visibility>
                        <initial-animation>Default</initial-animation>
                        <initial-frame>0</initial-frame>
                        <collisions>Enabled</collisions>
                    </properties>
                    <blend-mode>0</blend-mode>
                    <effect-fallback>0</effect-fallback>
                    <world>
                        <x>805</x>
                        <y>505</y>
                        <z>0</z>
                        <width>12</width>
                        <height>12</height>
                        <depth>0</depth>
                        <hotspotX>0.5</hotspotX>
                        <hotspotY>0.5</hotspotY>
                        <angle>0</angle>
                        <opacity>1</opacity>
                    </world>
                </instance>
                <instance type="m2_2_covfefeLight" uid="63">
                    <properties>
                        <initial-visibility>Visible</initial-visibility>
                        <initial-animation>Default</initial-animation>
                        <initial-frame>0</initial-frame>
                        <collisions>Enabled</collisions>
                    </properties>
                    <blend-mode>0</blend-mode>
                    <effect-fallback>0</effect-fallback>
                    <world>
                        <x>945</x>
                        <y>440</y>
                        <z>0</z>
                        <width>16</width>
                        <height>16</height>
                        <depth>0</depth>
                        <hotspotX>0.5</hotspotX>
                        <hotspotY>0.5</hotspotY>
                        <angle>0</angle>
                        <opacity>1</opacity>
                    </world>
                </instance>
            </instances>
            <effects />
        </layer>
        <layer name="light" sid="535646758494002">
            <initially-visible>1</initially-visible>
            <background-color>255,255,255</background-color>
            <transparent>1</transparent>
            <parallax>
                <x>1</x>
                <y>1</y>
            </parallax>
            <zoom-rate>1</zoom-rate>
            <opacity>1</opacity>
            <force-own-texture>1</force-own-texture>
            <global>0</global>
            <use-render-cells>0</use-render-cells>
            <blend-mode>0</blend-mode>
            <effect-fallback>0</effect-fallback>
            <instances>
                <instance type="m2_2_shd" uid="64">
                    <properties>
                        <initial-visibility>Visible</initial-visibility>
                        <initial-animation>Default</initial-animation>
                        <initial-frame>0</initial-frame>
                        <collisions>Enabled</collisions>
                    </properties>
                    <blend-mode>0</blend-mode>
                    <effect-fallback>0</effect-fallback>
                    <world>
                        <x>960</x>
                        <y>600</y>
                        <z>0</z>
                        <width>1920</width>
                        <height>1200</height>
                        <depth>0</depth>
                        <hotspotX>0.5</hotspotX>
                        <hotspotY>0.5</hotspotY>
                        <angle>0</angle>
                        <opacity>0.949999988</opacity>
                    </world>
                </instance>
                <instance type="m2_2_microwaveLite" uid="65">
                    <properties>
                        <initial-visibility>Visible</initial-visibility>
                        <initial-animation>Default</initial-animation>
                        <initial-frame>0</initial-frame>
                        <collisions>Enabled</collisions>
                    </properties>
                    <blend-mode>8</blend-mode>
                    <effect-fallback>0</effect-fallback>
                    <world>
                        <x>960</x>
                        <y>600</y>
                        <z>0</z>
                        <width>1920</width>
                        <height>1200</height>
                        <depth>0</depth>
                        <hotspotX>0.5</hotspotX>
                        <hotspotY>0.5</hotspotY>
                        <angle>0</angle>
                        <opacity>1</opacity>
                    </world>
                </instance>
                <instance type="m2_2_stoveLite" uid="66">
                    <properties>
                        <initial-visibility>Visible</initial-visibility>
                        <initial-animation>Default</initial-animation>
                        <initial-frame>0</initial-frame>
                        <collisions>Enabled</collisions>
                    </properties>
                    <blend-mode>8</blend-mode>
                    <effect-fallback>0</effect-fallback>
                    <world>
                        <x>960</x>
                        <y>600</y>
                        <z>0</z>
                        <width>1920</width>
                        <height>1200</height>
                        <depth>0</depth>
                        <hotspotX>0.5</hotspotX>
                        <hotspotY>0.5</hotspotY>
                        <angle>0</angle>
                        <opacity>0</opacity>
                    </world>
                </instance>
                <instance type="m2_2_fridgeLite" uid="67">
                    <properties>
                        <initial-visibility>Visible</initial-visibility>
                        <initial-animation>Default</initial-animation>
                        <initial-frame>0</initial-frame>
                        <collisions>Enabled</collisions>
                    </properties>
                    <blend-mode>8</blend-mode>
                    <effect-fallback>0</effect-fallback>
                    <world>
                        <x>960</x>
                        <y>600</y>
                        <z>0</z>
                        <width>1920</width>
                        <height>1200</height>
                        <depth>0</depth>
                        <hotspotX>0.5</hotspotX>
                        <hotspotY>0.5</hotspotY>
                        <angle>0</angle>
                        <opacity>0</opacity>
                    </world>
                </instance>
                <instance type="m2_2_microwaveLight" uid="68">
                    <properties>
                        <initial-visibility>Visible</initial-visibility>
                        <initial-animation>Default</initial-animation>
                        <initial-frame>0</initial-frame>
                        <collisions>Enabled</collisions>
                    </properties>
                    <blend-mode>0</blend-mode>
                    <effect-fallback>0</effect-fallback>
                    <world>
                        <x>940.333312988</x>
                        <y>170.333312988</y>
                        <z>0</z>
                        <width>14</width>
                        <height>14</height>
                        <depth>0</depth>
                        <hotspotX>0.5</hotspotX>
                        <hotspotY>0.5</hotspotY>
                        <angle>0</angle>
                        <opacity>1</opacity>
                    </world>
                </instance>
                <instance type="m2_2_toasterLight" uid="69">
                    <properties>
                        <initial-visibility>Visible</initial-visibility>
                        <initial-animation>Default</initial-animation>
                        <initial-frame>0</initial-frame>
                        <collisions>Enabled</collisions>
                    </properties>
                    <blend-mode>0</blend-mode>
                    <effect-fallback>0</effect-fallback>
                    <world>
                        <x>805.333312988</x>
                        <y>505.333312988</y>
                        <z>0</z>
                        <width>12</width>
                        <height>12</height>
                        <depth>0</depth>
                        <hotspotX>0.5</hotspotX>
                        <hotspotY>0.5</hotspotY>
                        <angle>0</angle>
                        <opacity>1</opacity>
                    </world>
                </instance>
                <instance type="m2_2_covfefeLight" uid="70">
                    <properties>
                        <initial-visibility>Visible</initial-visibility>
                        <initial-animation>Default</initial-animation>
                        <initial-frame>0</initial-frame>
                        <collisions>Enabled</collisions>
                    </properties>
                    <blend-mode>0</blend-mode>
                    <effect-fallback>0</effect-fallback>
                    <world>
                        <x>945.333312988</x>
                        <y>440.333312988</y>
                        <z>0</z>
                        <width>16</width>
                        <height>16</height>
                        <depth>0</depth>
                        <hotspotX>0.5</hotspotX>
                        <hotspotY>0.5</hotspotY>
                        <angle>0</angle>
                        <opacity>1</opacity>
                    </world>
                </instance>
                <instance type="m2_2_doorCrack" uid="71">
                    <properties>
                        <initial-visibility>Visible</initial-visibility>
                        <initial-animation>Default</initial-animation>
                        <initial-frame>0</initial-frame>
                        <collisions>Enabled</collisions>
                    </properties>
                    <blend-mode>0</blend-mode>
                    <effect-fallback>0</effect-fallback>
                    <world>
                        <x>273</x>
                        <y>930.5</y>
                        <z>0</z>
                        <width>532</width>
                        <height>273</height>
                        <depth>0</depth>
                        <hotspotX>0.5</hotspotX>
                        <hotspotY>0.5</hotspotY>
                        <angle>0</angle>
                        <opacity>0.5</opacity>
                    </world>
                </instance>
            </instances>
            <effects />
        </layer>
        <layer name="endGame" sid="191217521289828">
            <initially-visible>1</initially-visible>
            <background-color>255,255,255</background-color>
            <transparent>1</transparent>
            <parallax>
                <x>1</x>
                <y>1</y>
            </parallax>
            <zoom-rate>1</zoom-rate>
            <opacity>1</opacity>
            <force-own-texture>0</force-own-texture>
            <global>0</global>
            <use-render-cells>0</use-render-cells>
            <blend-mode>0</blend-mode>
            <effect-fallback>0</effect-fallback>
            <instances>
                <instance type="m2_2_endShade" uid="72">
                    <properties>
                        <initial-visibility>Visible</initial-visibility>
                        <initial-animation>Default</initial-animation>
                        <initial-frame>0</initial-frame>
                        <collisions>Enabled</collisions>
                    </properties>
                    <blend-mode>0</blend-mode>
                    <effect-fallback>0</effect-fallback>
                    <world>
                        <x>960</x>
                        <y>1849</y>
                        <z>0</z>
                        <width>1920</width>
                        <height>1200</height>
                        <depth>0</depth>
                        <hotspotX>0.5</hotspotX>
                        <hotspotY>0.5</hotspotY>
                        <angle>0</angle>
                        <opacity>0.75</opacity>
                    </world>
                </instance>
                <instance type="m2_2_endMenu" uid="73">
                    <properties>
                        <initial-visibility>Visible</initial-visibility>
                        <initial-animation>Default</initial-animation>
                        <initial-frame>0</initial-frame>
                        <collisions>Enabled</collisions>
                    </properties>
                    <blend-mode>0</blend-mode>
                    <effect-fallback>0</effect-fallback>
                    <world>
                        <x>1022</x>
                        <y>-454</y>
                        <z>0</z>
                        <width>1200</width>
                        <height>840</height>
                        <depth>0</depth>
                        <hotspotX>0.5</hotspotX>
                        <hotspotY>0.5</hotspotY>
                        <angle>0</angle>
                        <opacity>1</opacity>
                    </world>
                </instance>
                <instance type="m2_2_star" uid="74">
                    <properties>
                        <initial-visibility>Visible</initial-visibility>
                        <initial-animation>Default</initial-animation>
                        <initial-frame>0</initial-frame>
                        <collisions>Enabled</collisions>
                    </properties>
                    <blend-mode>0</blend-mode>
                    <effect-fallback>0</effect-fallback>
                    <world>
                        <x>722</x>
                        <y>-694</y>
                        <z>0</z>
                        <width>250</width>
                        <height>250</height>
                        <depth>0</depth>
                        <hotspotX>0.5</hotspotX>
                        <hotspotY>0.5</hotspotY>
                        <angle>0</angle>
                        <opacity>1</opacity>
                    </world>
                </instance>
                <instance type="m2_2_star2" uid="75">
                    <properties>
                        <initial-visibility>Visible</initial-visibility>
                        <initial-animation>Default</initial-animation>
                        <initial-frame>0</initial-frame>
                        <collisions>Enabled</collisions>
                    </properties>
                    <blend-mode>0</blend-mode>
                    <effect-fallback>0</effect-fallback>
                    <world>
                        <x>1022</x>
                        <y>-694</y>
                        <z>0</z>
                        <width>250</width>
                        <height>250</height>
                        <depth>0</depth>
                        <hotspotX>0.5</hotspotX>
                        <hotspotY>0.5</hotspotY>
                        <angle>0</angle>
                        <opacity>1</opacity>
                    </world>
                </instance>
                <instance type="m2_2_star3" uid="76">
                    <properties>
                        <initial-visibility>Visible</initial-visibility>
                        <initial-animation>Default</initial-animation>
                        <initial-frame>0</initial-frame>
                        <collisions>Enabled</collisions>
                    </properties>
                    <blend-mode>0</blend-mode>
                    <effect-fallback>0</effect-fallback>
                    <world>
                        <x>1322</x>
                        <y>-694</y>
                        <z>0</z>
                        <width>250</width>
                        <height>250</height>
                        <depth>0</depth>
                        <hotspotX>0.5</hotspotX>
                        <hotspotY>0.5</hotspotY>
                        <angle>0</angle>
                        <opacity>1</opacity>
                    </world>
                </instance>
                <instance type="m2_2_endDescription" uid="77">
                    <properties>
                        <text>Decription at end game</text>
                        <initial-visibility>Visible</initial-visibility>
                        <font>Arial,-37,400,0</font>
                        <color>0,0,0</color>
                        <horizontal-alignment>Center</horizontal-alignment>
                        <vertical-alignment>Top</vertical-alignment>
                        <hotspot>Center</hotspot>
                        <wrapping>Word</wrapping>
                        <line-height>0</line-height>
                    </properties>
                    <blend-mode>0</blend-mode>
                    <effect-fallback>0</effect-fallback>
                    <world>
                        <x>1022</x>
                        <y>-454</y>
                        <z>0</z>
                        <width>800</width>
                        <height>220</height>
                        <depth>0</depth>
                        <hotspotX>0.5</hotspotX>
                        <hotspotY>0.5</hotspotY>
                        <angle>0</angle>
                        <opacity>1</opacity>
                    </world>
                </instance>
                <instance type="m2_2_exit" uid="78">
                    <properties>
                        <initial-visibility>Visible</initial-visibility>
                        <initial-animation>Default</initial-animation>
                        <initial-frame>0</initial-frame>
                        <collisions>Enabled</collisions>
                    </properties>
                    <blend-mode>0</blend-mode>
                    <effect-fallback>0</effect-fallback>
                    <world>
                        <x>722</x>
                        <y>-254</y>
                        <z>0</z>
                        <width>240</width>
                        <height>240</height>
                        <depth>0</depth>
                        <hotspotX>0.5</hotspotX>
                        <hotspotY>0.5</hotspotY>
                        <angle>0</angle>
                        <opacity>1</opacity>
                    </world>
                </instance>
                <instance type="m2_2_retry" uid="79">
                    <properties>
                        <initial-visibility>Visible</initial-visibility>
                        <initial-animation>Default</initial-animation>
                        <initial-frame>0</initial-frame>
                        <collisions>Enabled</collisions>
                    </properties>
                    <blend-mode>0</blend-mode>
                    <effect-fallback>0</effect-fallback>
                    <world>
                        <x>1322</x>
                        <y>-254</y>
                        <z>0</z>
                        <width>240</width>
                        <height>240</height>
                        <depth>0</depth>
                        <hotspotX>0.5</hotspotX>
                        <hotspotY>0.5</hotspotY>
                        <angle>0</angle>
                        <opacity>1</opacity>
                    </world>
                </instance>
            </instances>
            <effects />
        </layer>
        <layer name="time" sid="429612036009515">
            <initially-visible>1</initially-visible>
            <background-color>255,255,255</background-color>
            <transparent>1</transparent>
            <parallax>
                <x>1</x>
                <y>1</y>
            </parallax>
            <zoom-rate>1</zoom-rate>
            <opacity>1</opacity>
            <force-own-texture>0</force-own-texture>
            <global>0</global>
            <use-render-cells>0</use-render-cells>
            <blend-mode>0</blend-mode>
            <effect-fallback>0</effect-fallback>
            <instances>
                <instance type="m2_2_timer" uid="58">
                    <properties>
                        <initial-visibility>Visible</initial-visibility>
                        <initial-animation>Default</initial-animation>
                        <initial-frame>0</initial-frame>
                        <collisions>Enabled</collisions>
                    </properties>
                    <blend-mode>0</blend-mode>
                    <effect-fallback>0</effect-fallback>
                    <world>
                        <x>960</x>
                        <y>20</y>
                        <z>0</z>
                        <width>1920</width>
                        <height>40</height>
                        <depth>0</depth>
                        <hotspotX>0.5</hotspotX>
                        <hotspotY>0.5</hotspotY>
                        <angle>0</angle>
                        <opacity>1</opacity>
                    </world>
                </instance>
                <instance type="m2_2_timerHolder" uid="59">
                    <properties>
                        <initial-visibility>Visible</initial-visibility>
                        <initial-animation>Default</initial-animation>
                        <initial-frame>0</initial-frame>
                        <collisions>Enabled</collisions>
                    </properties>
                    <blend-mode>0</blend-mode>
                    <effect-fallback>0</effect-fallback>
                    <world>
                        <x>960</x>
                        <y>20</y>
                        <z>0</z>
                        <width>1920</width>
                        <height>40</height>
                        <depth>0</depth>
                        <hotspotX>0.5</hotspotX>
                        <hotspotY>0.5</hotspotY>
                        <angle>0</angle>
                        <opacity>1</opacity>
                    </world>
                </instance>
                <instance type="m2_2_timerX2" uid="60">
                    <properties>
                        <initial-visibility>Visible</initial-visibility>
                        <initial-animation>Default</initial-animation>
                        <initial-frame>0</initial-frame>
                        <collisions>Enabled</collisions>
                    </properties>
                    <blend-mode>0</blend-mode>
                    <effect-fallback>0</effect-fallback>
                    <world>
                        <x>960</x>
                        <y>20</y>
                        <z>0</z>
                        <width>1920</width>
                        <height>40</height>
                        <depth>0</depth>
                        <hotspotX>0.5</hotspotX>
                        <hotspotY>0.5</hotspotY>
                        <angle>0</angle>
                        <opacity>1</opacity>
                    </world>
                </instance>
            </instances>
            <effects />
        </layer>
    </layers>
    <nonworld-instances />
    <effects />
</c2layout>
